biopragmatics/__init__.py
biopragmatics/__main__.py
biopragmatics/api.py
biopragmatics/cli.py
biopragmatics/py.typed
biopragmatics/version.py
biopragmatics-0.0.1.dist-info/LICENSE
biopragmatics-0.0.1.dist-info/METADATA
biopragmatics-0.0.1.dist-info/WHEEL
biopragmatics-0.0.1.dist-info/entry_points.txt
biopragmatics-0.0.1.dist-info/top_level.txt
biopragmatics-0.0.1.dist-info/RECORD
